Metadata-Version: 2.1
Name: lickit
Version: 0.1.0
Summary: A toolkit for breaking licensing restrictions.
Home-page: https://github.com/Aunity/lickit
Author: Aunity
Author-email: maohuay@hotmail.com
Keywords: License
License-File: LICENSE
